Workbook

Sheet Assumptions
A1: Parameter | B1: Value | C1: Source / Rationale
A3: UPFRONT COSTS (One-Time)
A4: Pty Ltd Registration (ASIC) | B4: 576 | C4: Source: register.business.gov.au, 2026
A5: Director ID Application | B5: 0 | C5: Free via abrs.gov.au
A6: Business Name Registration (3yr) | B6: 98 | C6: Source: ASIC, $42/yr or $98/3yr
A7: Legal Review (Terms + Privacy) | B7: 3500 | C7: Estimate: Australian technology lawyer, 2026. Yellow = key assumption.
A8: PI + Cyber Insurance (Year 1) | B8: 1500 | C8: Source: Startupcover/BizCover, $900-$2,000 range. Midpoint used.
A9: Domain (sagereasoning.com) - already owned | B9: 0 | C9: Already purchased
A10: Stripe Setup | B10: 0 | C10: Free to set up; per-transaction fees apply
A11: TOTAL UPFRONT INVESTMENT | B11: =SUM(B4:B10) -> 5674
A13: MONTHLY FIXED COSTS
A14: Vercel Hosting (Pro) | B14: 20 | C14: Source: vercel.com pricing, 2026
A15: Supabase (Pro) | B15: 25 | C15: Source: supabase.com pricing, 2026
A16: Accounting Software (Xero) | B16: 29 | C16: Source: xero.com.au, Starter plan
A17: Insurance (amortised monthly) | B17: 125 | C17: $1,500/12. Conservative midpoint.
A18: ASIC Annual Fee (amortised monthly) | B18: 48 | C18: $576/12
A19: Domain Renewal (amortised monthly) | B19: 2 | C19: ~$20/year
A20: Email Service (Resend/Buttondown) | B20: 0 | C20: Free tier sufficient initially
A21: Miscellaneous/Buffer | B21: 30 | C21: Contingency for minor costs
A22: TOTAL MONTHLY FIXED COSTS | B22: =SUM(B14:B21) -> 279
A24: VARIABLE COST ASSUMPTIONS
A25: Anthropic API cost per scoring call | B25: 0.015 | C25: Claude Sonnet input+output for scoring prompt. Yellow = key assumption.
A26: API markup (revenue per call / cost per call) | B26: 2 | C26: 200% of Anthropic cost = 100% gross margin on API calls
A27: Revenue per API call | B27: =B25*B26 -> 0.03
A28: Gross margin per API call | B28: =B27-B25 -> 0.015
A29: Stripe fee per transaction | B29: 1.75% + $0.30 | C29: Source: stripe.com.au, 2026
A31: CONVERSION & GROWTH ASSUMPTIONS
A32: Free-to-Paid conversion rate (human Prokoptos) | B32: 0.05 | C32: 5% conservative. Industry SaaS freemium: 2-5%. Niche = higher intent.
A33: Agent free-to-paid conversion rate | B33: 0.08 | C33: 8%. Developers evaluating with free tier have high intent if product fits.
A34: Prokoptos monthly subscription price | B34: 7
A35: Avg paid agent API calls/month per developer | B35: 2000 | C35: Conservative. PMF doc notes 1,000-5,000 range for active integrations.
A36: Patronage rate (% of free users) | B36: 0.03 | C36: 3%. Research says 1-5% for mission-driven platforms.
A37: Avg patronage amount/month | B37: 5

Sheet 12-Month Projection
B1: Month 1 | C1: Month 2 | D1: Month 3 | E1: Month 4 | F1: Month 5 | G1: Month 6 | H1: Month 7 | I1: Month 8 | J1: Month 9 | K1: Month 10 | L1: Month 11 | M1: Month 12 | N1: TOTAL
A3: USER GROWTH (Cumulative)
A4: Registered Human Users (cumulative) | B4: 20 | C4: 50 | D4: 100 | E4: 170 | F4: 260 | G4: 370 | H4: 500 | I4: 650 | J4: 820 | K4: 1000 | L4: 1200 | M4: 1400
A5: Agent Developers Registered (cumulative) | B5: 5 | C5: 12 | D5: 25 | E5: 40 | F5: 60 | G5: 85 | H5: 115 | I5: 150 | J5: 190 | K5: 235 | L5: 285 | M5: 340
A7: PAYING CUSTOMERS
A8: Prokoptos Subscribers (human) | B8: =ROUND(B4*Assumptions!B32,0) -> 1 | C8: =ROUND(C4*Assumptions!B32,0) -> 3 | D8: =ROUND(D4*Assumptions!B32,0) -> 5 | E8: =ROUND(E4*Assumptions!B32,0) -> 9 | F8: =ROUND(F4*Assumptions!B32,0) -> 13 | G8: =ROUND(G4*Assumptions!B32,0) -> 19 | H8: =ROUND(H4*Assumptions!B32,0) -> 25 | I8: =ROUND(I4*Assumptions!B32,0) -> 33 | J8: =ROUND(J4*Assumptions!B32,0) -> 41 | K8: =ROUND(K4*Assumptions!B32,0) -> 50 | L8: =ROUND(L4*Assumptions!B32,0) -> 60 | M8: =ROUND(M4*Assumptions!B32,0) -> 70
A9: Paid Agent Developers | B9: =ROUND(B5*Assumptions!B33,0) -> 0 | C9: =ROUND(C5*Assumptions!B33,0) -> 1 | D9: =ROUND(D5*Assumptions!B33,0) -> 2 | E9: =ROUND(E5*Assumptions!B33,0) -> 3 | F9: =ROUND(F5*Assumptions!B33,0) -> 5 | G9: =ROUND(G5*Assumptions!B33,0) -> 7 | H9: =ROUND(H5*Assumptions!B33,0) -> 9 | I9: =ROUND(I5*Assumptions!B33,0) -> 12 | J9: =ROUND(J5*Assumptions!B33,0) -> 15 | K9: =ROUND(K5*Assumptions!B33,0) -> 19 | L9: =ROUND(L5*Assumptions!B33,0) -> 23 | M9: =ROUND(M5*Assumptions!B33,0) -> 27
A10: Patrons (free users contributing) | B10: =ROUND((B4-B8)*Assumptions!B36,0) -> 1 | C10: =ROUND((C4-C8)*Assumptions!B36,0) -> 1 | D10: =ROUND((D4-D8)*Assumptions!B36,0) -> 3 | E10: =ROUND((E4-E8)*Assumptions!B36,0) -> 5 | F10: =ROUND((F4-F8)*Assumptions!B36,0) -> 7 | G10: =ROUND((G4-G8)*Assumptions!B36,0) -> 11 | H10: =ROUND((H4-H8)*Assumptions!B36,0) -> 14 | I10: =ROUND((I4-I8)*Assumptions!B36,0) -> 19 | J10: =ROUND((J4-J8)*Assumptions!B36,0) -> 23 | K10: =ROUND((K4-K8)*Assumptions!B36,0) -> 29 | L10: =ROUND((L4-L8)*Assumptions!B36,0) -> 34 | M10: =ROUND((M4-M8)*Assumptions!B36,0) -> 40
A12: REVENUE
A13: Prokoptos Subscription Revenue | B13: =B8*Assumptions!B34 -> 7 | C13: =C8*Assumptions!B34 -> 21 | D13: =D8*Assumptions!B34 -> 35 | E13: =E8*Assumptions!B34 -> 63 | F13: =F8*Assumptions!B34 -> 91 | G13: =G8*Assumptions!B34 -> 133 | H13: =H8*Assumptions!B34 -> 175 | I13: =I8*Assumptions!B34 -> 231 | J13: =J8*Assumptions!B34 -> 287 | K13: =K8*Assumptions!B34 -> 350 | L13: =L8*Assumptions!B34 -> 420 | M13: =M8*Assumptions!B34 -> 490
A14: Agent API Revenue (paid calls) | B14: =B9*Assumptions!B35*Assumptions!B27 -> 0 | C14: =C9*Assumptions!B35*Assumptions!B27 -> 60 | D14: =D9*Assumptions!B35*Assumptions!B27 -> 120 | E14: =E9*Assumptions!B35*Assumptions!B27 -> 180 | F14: =F9*Assumptions!B35*Assumptions!B27 -> 300 | G14: =G9*Assumptions!B35*Assumptions!B27 -> 420 | H14: =H9*Assumptions!B35*Assumptions!B27 -> 540 | I14: =I9*Assumptions!B35*Assumptions!B27 -> 720 | J14: =J9*Assumptions!B35*Assumptions!B27 -> 900 | K14: =K9*Assumptions!B35*Assumptions!B27 -> 1140 | L14: =L9*Assumptions!B35*Assumptions!B27 -> 1380 | M14: =M9*Assumptions!B35*Assumptions!B27 -> 1620
A15: Patronage Revenue | B15: =B10*Assumptions!B37 -> 5 | C15: =C10*Assumptions!B37 -> 5 | D15: =D10*Assumptions!B37 -> 15 | E15: =E10*Assumptions!B37 -> 25 | F15: =F10*Assumptions!B37 -> 35 | G15: =G10*Assumptions!B37 -> 55 | H15: =H10*Assumptions!B37 -> 70 | I15: =I10*Assumptions!B37 -> 95 | J15: =J10*Assumptions!B37 -> 115 | K15: =K10*Assumptions!B37 -> 145 | L15: =L10*Assumptions!B37 -> 170 | M15: =M10*Assumptions!B37 -> 200
A16: Virtue Badges / Accessories (net) | B16: 0 | C16: 0 | D16: 0 | E16: 45 | F16: 60 | G16: 80 | H16: 100 | I16: 120 | J16: 140 | K16: 150 | L16: 160 | M16: 180
A17: Enterprise Licensing | B17: 0 | C17: 0 | D17: 0 | E17: 0 | F17: 0 | G17: 0 | H17: 0 | I17: 0 | J17: 500 | K17: 500 | L17: 500 | M17: 500
A18: TOTAL MONTHLY REVENUE | B18: =SUM(B13:B17) -> 12 | C18: =SUM(C13:C17) -> 86 | D18: =SUM(D13:D17) -> 170 | E18: =SUM(E13:E17) -> 313 | F18: =SUM(F13:F17) -> 486 | G18: =SUM(G13:G17) -> 688 | H18: =SUM(H13:H17) -> 885 | I18: =SUM(I13:I17) -> 1166 | ... M18: =SUM(M13:M17) -> 2990 | N18: =SUM(B18:M18) -> 13653
A20: COSTS
A21: Monthly Fixed Costs | B21: =Assumptions!B22 -> 279 | C21: =Assumptions!B22 -> 279 | D21: =Assumptions!B22 -> 279 | E21: =Assumptions!B22 -> 279 | F21: =Assumptions!B22 -> 279 | G21: =Assumptions!B22 -> 279 | H21: =Assumptions!B22 -> 279 | I21: =Assumptions!B22 -> 279 | J21: =Assumptions!B22 -> 279 | K21: =Assumptions!B22 -> 279 | L21: =Assumptions!B22 -> 279 | M21: =Assumptions!B22 -> 279
A22: Anthropic API Costs (paid agent calls) | B22: =B9*Assumptions!B35*Assumptions!B25 -> 0 | C22: =C9*Assumptions!B35*Assumptions!B25 -> 30 | D22: =D9*Assumptions!B35*Assumptions!B25 -> 60 | E22: =E9*Assumptions!B35*Assumptions!B25 -> 90 | F22: =F9*Assumptions!B35*Assumptions!B25 -> 150 | G22: =G9*Assumptions!B35*Assumptions!B25 -> 210 | H22: =H9*Assumptions!B35*Assumptions!B25 -> 270 | I22: =I9*Assumptions!B35*Assumptions!B25 -> 360 | J22: =J9*Assumptions!B35*Assumptions!B25 -> 450 | K22: =K9*Assumptions!B35*Assumptions!B25 -> 570 | L22: =L9*Assumptions!B35*Assumptions!B25 -> 690 | M22: =M9*Assumptions!B35*Assumptions!B25 -> 810
A23: Anthropic API Costs (free tier + human scoring) | B23: 15 | C23: 20 | D23: 30 | E23: 40 | F23: 50 | G23: 60 | H23: 70 | I23: 80 | J23: 90 | K23: 100 | L23: 110 | M23: 120
A24: Stripe Transaction Fees (~2%) | B24: =B18*0.02 -> 0.24 | C24: =C18*0.02 -> 1.72 | D24: =D18*0.02 -> 3.4 | E24: =E18*0.02 -> 6.26 | F24: =F18*0.02 -> 9.72 | G24: =G18*0.02 -> 13.76 | H24: =H18*0.02 -> 17.7 | I24: =I18*0.02 -> 23.32 | ... M24: =M18*0.02 -> 59.8
A25: TOTAL MONTHLY COSTS | B25: =SUM(B21:B24) -> 294.24 | C25: =SUM(C21:C24) -> 330.72 | D25: =SUM(D21:D24) -> 372.4 | E25: =SUM(E21:E24) -> 415.26 | F25: =SUM(F21:F24) -> 488.72 | G25: =SUM(G21:G24) -> 562.76 | H25: =SUM(H21:H24) -> 636.7 | I25: =SUM(I21:I24) -> 742.32 | ... M25: =SUM(M21:M24) -> 1268.8 | N25: =SUM(B25:M25) -> 8096.06
A27: NET POSITION
A28: Monthly Net (Revenue - Costs) | B28: =B18-B25 -> -282.24 | C28: =C18-C25 -> -244.72 | D28: =D18-D25 -> -202.4 | E28: =E18-E25 -> -102.26 | F28: =F18-F25 -> -2.72 | G28: =G18-G25 -> 125.24 | H28: =H18-H25 -> 248.3 | I28: =I18-I25 -> 423.68 | ... M28: =M18-M25 -> 1721.2
A29: Cumulative Net (incl. upfront costs) | B29: =-Assumptions!B11+B28 -> -5956.24 | C29: =B29+C28 -> -6200.96 | D29: =C29+D28 -> -6403.36 | E29: =D29+E28 -> -6505.62 | F29: =E29+F28 -> -6508.34 | G29: =F29+G28 -> -6383.1 | H29: =G29+H28 -> -6134.8 | I29: =H29+I28 -> -5711.12 | J29: =I29+J28 -> -4626.96 | ... M29: =L29+M28 -> -117.06
A31: Gross Margin on API Revenue | B31: =IF(B14=0,0,(B14-B22)/B14) -> 0 | C31: =IF(C14=0,0,(C14-C22)/C14) -> 0.5 | D31: =IF(D14=0,0,(D14-D22)/D14) -> 0.5 | E31: =IF(E14=0,0,(E14-E22)/E14) -> 0.5 | F31: =IF(F14=0,0,(F14-F22)/F14) -> 0.5 | G31: =IF(G14=0,0,(G14-G22)/G14) -> 0.5 | H31: =IF(H14=0,0,(H14-H22)/H14) -> 0.5 | I31: =IF(I14=0,0,(I14-I22)/I14) -> 0.5 | ... M31: =IF(M14=0,0,(M14-M22)/M14) -> 0.5

Sheet Scenario Analysis
B1: Bear Case | C1: Base Case | D1: Bull Case | E1: Notes
A3: 12-MONTH END STATE
A4: Registered Human Users | B4: 600 | C4: 1400 | D4: 3000 | E4: Bear = slow organic. Bull = HN/PH viral moment.
A5: Agent Developers Registered | B5: 80 | C5: 340 | D5: 800
A6: Human Conversion Rate | B6: 0.03 | C6: 0.05 | D6: 0.1
A7: Agent Conversion Rate | B7: 0.04 | C7: 0.08 | D7: 0.15
A8: Avg Paid Agent Calls/Month | B8: 500 | C8: 2000 | D8: 5000
A10: MONTH 12 REVENUE (MONTHLY)
A11: Prokoptos Subscribers | B11: =ROUND(B4*B6,0) -> 18 | C11: =ROUND(C4*C6,0) -> 70 | D11: =ROUND(D4*D6,0) -> 300
A12: Paid Agent Developers | B12: =ROUND(B5*B7,0) -> 3 | C12: =ROUND(C5*C7,0) -> 27 | D12: =ROUND(D5*D7,0) -> 120
A13: Prokoptos Revenue/month | B13: =B11*Assumptions!B34 -> 126 | C13: =C11*Assumptions!B34 -> 490 | D13: =D11*Assumptions!B34 -> 2100
A14: Agent API Revenue/month | B14: =B12*B8*Assumptions!B27 -> 45 | C14: =C12*C8*Assumptions!B27 -> 1620 | D14: =D12*D8*Assumptions!B27 -> 18000
A15: Other Revenue (patronage + badges + enterprise) | B15: 50 | C15: 350 | D15: 1000
A16: TOTAL MONTH 12 REVENUE | B16: =SUM(B13:B15) -> 221 | C16: =SUM(C13:C15) -> 2460 | D16: =SUM(D13:D15) -> 21100
A18: MONTH 12 COSTS (MONTHLY)
A19: Fixed Costs/month | B19: =Assumptions!B22 -> 279 | C19: =Assumptions!B22 -> 279 | D19: =Assumptions!B22 -> 279
A20: API Variable Costs/month | B20: =B12*B8*Assumptions!B25+100 -> 122.5 | C20: =C12*C8*Assumptions!B25+100 -> 910 | D20: =D12*D8*Assumptions!B25+100 -> 9100
A21: TOTAL MONTH 12 COSTS | B21: =B19+B20 -> 401.5 | C21: =C19+C20 -> 1189 | D21: =D19+D20 -> 9379
A23: VERDICTS
A24: Month 12 Net (Revenue - Costs) | B24: =B16-B21 -> -180.5 | C24: =C16-C21 -> 1271 | D24: =D16-D21 -> 11721
A25: Annualised Run Rate (Month 12 x 12) | B25: =B16*12 -> 2652 | C25: =C16*12 -> 29520 | D25: =D16*12 -> 253200
A26: Break-Even Prokoptos Subs (fixed costs only) | B26: =ROUND(Assumptions!B22/Assumptions!B34,0) -> 40 | C26: (If ONLY Prokoptos revenue, no API)
A28: Total Upfront Investment Required | B28: =Assumptions!B11 -> 5674
A29: Maximum capital at risk (upfront + 6 months losses) | B29: =Assumptions!B11+6*Assumptions!B22 -> 7348 | C29: Worst case: 6 months of losses before pivoting

Sheet Break-Even Analysis
A1: Break-Even Metric | B1: Value | C1: Explanation
A3: SCENARIO A: Prokoptos Only (No API Revenue)
A4: Monthly fixed costs | B4: =Assumptions!B22 -> 279
A5: Net revenue per Prokoptos sub (after Stripe) | B5: =Assumptions!B34*(1-0.02) -> 6.86
A6: Subscribers needed to break even | B6: =ROUNDUP(B4/B5,0) -> 41 | C6: This is the hardest path. Requires ~40 paying humans.
A7: Registered users needed (at 5% conversion) | B7: =ROUNDUP(B6/Assumptions!B32,0) -> 820
A9: SCENARIO B: Prokoptos + 5 Paid Agent Developers
A10: Monthly API gross margin from 5 agents | B10: =5*Assumptions!B35*Assumptions!B28 -> 150
A11: Remaining fixed costs after API margin | B11: =MAX(B4-B10,0) -> 129
A12: Additional Prokoptos subs needed | B12: =IF(B11=0,0,ROUNDUP(B11/B5,0)) -> 19
A14: SCENARIO C: API Revenue Only (No Prokoptos)
A15: Gross margin per API call | B15: =Assumptions!B28 -> 0.015
A16: API calls/month needed to cover fixed costs | B16: =ROUNDUP(B4/B15,0) -> 18600
A17: Paid developers needed (at 2,000 calls/month each) | B17: =ROUNDUP(B16/Assumptions!B35,0) -> 10
A19: PAYBACK PERIOD ON UPFRONT INVESTMENT
A20: Total upfront investment | B20: =Assumptions!B11 -> 5674
A21: Avg monthly net income (base case, months 7-12) | B21: =AVERAGE('12-Month Projection'!H28:M28) -> 1044.34
A22: Months to recoup upfront (from Month 7) | B22: =IF(B21>0,ROUNDUP(B20/B21,1),"N/A") -> 5.5

Sheet Conversion Funnel
A1: Funnel Stage | B1: Agent Track | C1: Human Track | D1: Conversion % | E1: Rationale / Risk Factor
A3: AGENT DEVELOPER FUNNEL (Month 12 Base Case)
A4: Discovers SageReasoning (MCP registry, GitHub, API dirs) | B4: 3400 | D4: 100% | E4: Impressions from MCP registries, HN post, API directories
A5: Visits API docs / reads llms.txt | B5: 680 | D5: 20% | E5: Standard developer discovery-to-docs rate
A6: Registers for free API key | B6: 340 | D6: 50% | E6: Low friction: email only. 50% of docs visitors try it.
A7: Runs free Foundational Check (11 assessments) | B7: 272 | D7: 80% | E7: NEW: Free tier now gives meaningful standalone value
A8: Sees CTA with personalised tier result | B8: 272 | D8: 100% | E8: Automatic — shown after free assessment
A9: Upgrades to paid API key | B9: 27 | D9: 10% | E9: 8% conversion on registered base. ~10% of CTA viewers.
A10: Active paid user after Month 1 | B10: 20 | D10: 75% | E10: Retention: 75% of paid developers remain active
A12: HUMAN USER FUNNEL (Month 12 Base Case)
A13: Discovers SageReasoning (SEO, Reddit, Stoic Week) | C13: 7000 | D13: 100% | E13: Impressions from SEO articles, Reddit, community posts
A14: Visits website | C14: 2100 | D14: 30% | E14: Higher than agent track: Stoic community word-of-mouth
A15: Creates account (free Agora tier) | C15: 1400 | D15: 67% | E15: Free tier is generous; Stoic community = high intent
A16: Completes baseline assessment | C16: 840 | D16: 60% | E16: Free and immediate value. No payment gate.
A17: Engages with journal / scenarios | C17: 420 | D17: 50% | E17: Ongoing use requires motivation and habit formation
A18: Converts to Prokoptos ($7/mo) | C18: 70 | D18: 17% | E18: 5% of registered base. 17% of active engagers.
A19: Retains after Month 1 | C19: 53 | D19: 75% | E19: Niche = higher retention than general SaaS (60-80%)
A21: KEY FUNNEL INSIGHT: NEW TIER ARCHITECTURE IMPACT
A22: Old model: Payment gate BEFORE value | B22: Estimated 2-3% conversion
A23: New model: Free 11-assessment result THEN payment | B23: Estimated 8-10% conversion
A24: Impact: 3-4x improvement in agent conversion rate | E24: AX research validated that deposit-before-value was primary conversion risk
